footballscoring/__init__.py
footballscoring/definitions.py
footballscoring/gameclock.py
footballscoring/gameconfig.py
footballscoring/gamestate.py
footballscoring-0.2.dist-info/METADATA
footballscoring-0.2.dist-info/RECORD
footballscoring-0.2.dist-info/WHEEL
footballscoring-0.2.dist-info/top_level.txt
tests/__init__.py
tests/test_constraints.py
tests/test_gameclock.py
tests/test_gamestate.py
