Metadata-Version: 2.1
Name: footballscoring
Version: 0.2
Summary: A utility package for managing a american football game, including scoring, down, distance and so on, Game Clock and game setup with team names and logos. Can be used for further implementation like live tickersor displaying scoreboards.
Home-page: https://github.com/zapfdk/pyfootballscoring
Author: Dominik Zapf
Author-email: dominik.zapf@tu-ilmenau.de
License: Apache License 2.0
Keywords: american football scoring scoreboard liveticker
Platform: UNKNOWN
Classifier: Development Status :: 4 - Beta
Classifier: Topic :: Utilities
Classifier: License :: OSI Approved :: Apache Software License
Requires-Dist: apscheduler
